mdev/__init__.py
mdev/build.py
mdev/env.py
mdev/flash.py
mdev/log.py
mdev/main.py
mdev/project_management.py
mdev/mflash/__init__.py
mdev/mflash/mflash.py
mdev/mflash/flashloader/ramcode/mx1270.elf
mdev/mflash/flashloader/ramcode/mx1290.elf
mdev/mflash/flashloader/ramcode/mx1300.elf
mdev/mflash/flashloader/ramcode/mx1310.elf
mdev/mflash/flashloader/ramcode/mx1350.elf
mdev/mflash/flashloader/ramcode/rtl8710ec.elf
mdev/mflash/flashloader/ramcode/rtl8762c.elf
mdev/mflash/flashloader/scripts/cmd.tcl
mdev/mflash/flashloader/scripts/flash.tcl
mdev/mflash/interface/jlink_swd.cfg
mdev/mflash/interface/mxlink.cfg
mdev/mflash/interface/swj-dp.tcl
mdev/mflash/openocd/osx/libftdi1.2.dylib
mdev/mflash/openocd/osx/libhidapi.0.dylib
mdev/mflash/openocd/osx/libusb-0.1.4.dylib
mdev/mflash/openocd/osx/libusb-1.0.0.dylib
mdev/mflash/openocd/osx/openocd_mxos
mdev/mflash/openocd/osx/openocd_mxos_dirname
mdev/mflash/openocd/osx/openocd_mxos_run
mdev/mflash/openocd/win/libftdi1.dll
mdev/mflash/openocd/win/libhidapi-0.dll
mdev/mflash/openocd/win/libusb-0-1-4.dll
mdev/mflash/openocd/win/libusb-1.0.dll
mdev/mflash/openocd/win/openocd_mxos.exe
mdev/mflash/targets/mx1270.cfg
mdev/mflash/targets/mx1290.cfg
mdev/mflash/targets/mx1300.cfg
mdev/mflash/targets/mx1310.cfg
mdev/mflash/targets/mx1350.cfg
mdev/mflash/targets/rtl8710ec.cfg
mdev/mflash/targets/rtl8762c.cfg
mdev/templates/.gitignore
mdev/templates/.mdev
mdev/templates/CMakeLists.txt
mdev/templates/Kconfig
mdev/templates/app/CMakeLists.txt
mdev/templates/app/main.c
mdev/templates/app/mxos_config.h
mdev-0.4.4.dist-info/licenses/LICENSE
mdev-0.4.4.dist-info/METADATA
mdev-0.4.4.dist-info/WHEEL
mdev-0.4.4.dist-info/entry_points.txt
mdev-0.4.4.dist-info/top_level.txt
mdev-0.4.4.dist-info/RECORD
