Metadata-Version: 2.4
Name: mdev
Version: 0.4.4
Summary: Tool for build MXOS application.
Home-page: https://github.com/smartsnow/mdev
Author: Snow Yang
Author-email: snowyang.iot@outlook.com
Project-URL: Bug Tracker, https://github.com/smartsnow/mdev/issues
Classifier: Programming Language :: Python :: 3
Classifier: License :: OSI Approved :: MIT License
Classifier: Operating System :: OS Independent
Requires-Python: >=3.6
License-File: LICENSE
Requires-Dist: rich
Requires-Dist: click
Requires-Dist: requests
Requires-Dist: colorama
Requires-Dist: tqdm
Requires-Dist: kconfiglib
Dynamic: license-file
